navground/learning/__init__.py
navground/learning/indices.py
navground/learning/io.py
navground/learning/py.typed
navground/learning/register.py
navground/learning/rewards.py
navground/learning/types.py
navground/learning/behaviors/__init__.py
navground/learning/behaviors/pad/__init__.py
navground/learning/behaviors/pad/centralized.py
navground/learning/behaviors/pad/distributed.py
navground/learning/behaviors/pad/stop.py
navground/learning/behaviors/policy/__init__.py
navground/learning/behaviors/policy/base.py
navground/learning/behaviors/policy/group.py
navground/learning/behaviors/policy/single.py
navground/learning/config/__init__.py
navground/learning/config/base.py
navground/learning/config/binary_control_action.py
navground/learning/config/control_action.py
navground/learning/config/control_action_with_comm.py
navground/learning/config/discrete_control_action.py
navground/learning/config/discrete_control_action_with_comm.py
navground/learning/config/group.py
navground/learning/config/modulation_action.py
navground/learning/config/observation.py
navground/learning/config/state.py
navground/learning/env/__init__.py
navground/learning/env/env.py
navground/learning/evaluation/__init__.py
navground/learning/evaluation/evaluate_policies.py
navground/learning/evaluation/evaluate_policy.py
navground/learning/evaluation/experiment.py
navground/learning/evaluation/logging.py
navground/learning/evaluation/navground.py
navground/learning/evaluation/scenario.py
navground/learning/evaluation/video.py
navground/learning/examples/__init__.py
navground/learning/examples/corridor_with_obstacle.py
navground/learning/examples/cross.py
navground/learning/examples/pad/__init__.py
navground/learning/experimental/__init__.py
navground/learning/experimental/discrete_modulation.py
navground/learning/experimental/policy_behavior_modulation.py
navground/learning/experimental/selection_behavior.py
navground/learning/il/__init__.py
navground/learning/il/base.py
navground_learning-0.2.0.dist-info/licenses/LICENSE
navground_learning-0.2.0.dist-info/METADATA
navground_learning-0.2.0.dist-info/WHEEL
navground_learning-0.2.0.dist-info/entry_points.txt
navground_learning-0.2.0.dist-info/top_level.txt
navground_learning-0.2.0.dist-info/RECORD
