Metadata-Version: 2.4
Name: navground_learning
Version: 0.2.0
Summary: A Python package that interfaces navground with ML-libraries to learn navigating using IL and RL.
Author-email: Jerome Guzzi <jerome@idsia.ch>
Maintainer-email: Jerome Guzzi <jerome@idsia.ch>
License: MIT License
Project-URL: Homepage, https://github.com/idsia-robotics/navground_learning
Project-URL: Documentation, https://idsia-robotics.github.io/navground_learning
Project-URL: Repository, https://github.com/idsia-robotics/navground_learning.git
Project-URL: Bug Tracker, https://github.com/idsia-robotics/navground_learning/issues
Project-URL: Changelog, https://github.com/idsia-robotics/navground_learning/blob/main/CHANGELOG.md
Keywords: navigation,navground,gymnasium,pettingzoo,torchrl,imitation-learning,reinforcement-learning
Classifier: Development Status :: 4 - Beta
Classifier: Programming Language :: Python :: 3
Classifier: Intended Audience :: Science/Research
Classifier: Intended Audience :: Education
Classifier: Topic :: Scientific/Engineering :: Artificial Intelligence
Classifier: Typing :: Typed
Requires-Python: >=3.10
License-File: LICENSE
Requires-Dist: gymnasium>=1.0.0
Requires-Dist: navground>=0.6.0
Requires-Dist: pettingzoo>=1.24.3
Provides-Extra: rl
Requires-Dist: stable-baselines3>=2.4.0; extra == "rl"
Requires-Dist: SuperSuit>=3.9.3; extra == "rl"
Provides-Extra: il
Requires-Dist: imitation>=1.0.0; extra == "il"
Requires-Dist: SuperSuit>=3.9.3; extra == "il"
Provides-Extra: inference
Requires-Dist: onnxruntime>=1.20.0; extra == "inference"
Requires-Dist: onnx; extra == "inference"
Provides-Extra: torchrl
Requires-Dist: benchmarl; extra == "torchrl"
Requires-Dist: torchrl; extra == "torchrl"
Provides-Extra: all
Requires-Dist: navground[all]; extra == "all"
Requires-Dist: pettingzoo>=1.24.3; extra == "all"
Requires-Dist: SuperSuit>=3.9.3; extra == "all"
Requires-Dist: stable-baselines3>=2.4.0; extra == "all"
Requires-Dist: imitation>=1.0.0; extra == "all"
Requires-Dist: onnxruntime; extra == "all"
Requires-Dist: torch>=2.4; extra == "all"
Requires-Dist: onnx; extra == "all"
Requires-Dist: tqdm; extra == "all"
Requires-Dist: benchmarl; extra == "all"
Requires-Dist: torchrl; extra == "all"
Requires-Dist: pandas; extra == "all"
Requires-Dist: matplotlib; extra == "all"
Dynamic: license-file
